mcp_tech_shrimp_mcp_demo/__init__.py
mcp_tech_shrimp_mcp_demo-0.1.0.dist-info/METADATA
mcp_tech_shrimp_mcp_demo-0.1.0.dist-info/WHEEL
mcp_tech_shrimp_mcp_demo-0.1.0.dist-info/entry_points.txt
mcp_tech_shrimp_mcp_demo-0.1.0.dist-info/RECORD
