Metadata-Version: 2.4
Name: mcp-tech-shrimp-mcp-demo
Version: 0.1.0
Summary: Add your description here
Author-email: fernbruce <171006308@qq.com>
Requires-Python: >=3.13
Requires-Dist: mcp[cli]>=1.9.3
